LICENSE
README.md
lyybinary.py
setup.py
lyybinary.egg-info/PKG-INFO
lyybinary.egg-info/SOURCES.txt
lyybinary.egg-info/dependency_links.txt
lyybinary.egg-info/top_level.txt