Metadata-Version: 2.1
Name: lyybinary
Version: 2.18
Summary: calendar for  lyy
Author: lyy
Author-email: 
License: MIT
License-File: LICENSE
